langchain_dappier/__init__.py
langchain_dappier/py.typed
langchain_dappier/retrievers.py
langchain_dappier/tools.py
langchain_dappier-0.2.4.dist-info/LICENSE
langchain_dappier-0.2.4.dist-info/METADATA
langchain_dappier-0.2.4.dist-info/WHEEL
langchain_dappier-0.2.4.dist-info/RECORD
